{
    "namePrefix": "R30D09",
    "status": 0,
    "bgMd5": "04B87B89EAFDF12D13C8F07E48AAF212",
    "bgTexSize": {
        "x": 640,
        "y": 480
    },
    "texDumpMatches": [
        {
            "formatName": "RE3 SourceNext",
            "texNames": [
                "R30D09"
            ],
            "partIndices": [
                0
            ]
        },
        {
            "formatName": "RE3 GameCube",
            "texNames": [
                "tex1_640x480_a3f722d2162a49b7_5"
            ],
            "partIndices": [
                0
            ]
        }
    ],
    "hasMask": false,
    "camPosIndex": 0,
    "groupsCount": 0,
    "maskMd5": "",
    "maskTexSize": {
        "x": 0,
        "y": 0
    },
    "useProcessedMaskTex": false,
    "isReversedMaskOrder": false,
    "masks": []
}