{
    "namePrefix": "R11A08",
    "status": 0,
    "bgMd5": "06373F67667F1F035495DF63B8D5D214",
    "bgTexSize": {
        "x": 640,
        "y": 480
    },
    "texDumpMatches": [
        {
            "formatName": "RE3 SourceNext",
            "texNames": [
                "R11A08"
            ],
            "partIndices": [
                0
            ]
        },
        {
            "formatName": "RE3 GameCube",
            "texNames": [
                "tex1_640x480_4b7c0d7e61674c9e_5"
            ],
            "partIndices": [
                0
            ]
        }
    ],
    "hasMask": false,
    "camPosIndex": 0,
    "groupsCount": 0,
    "maskMd5": "",
    "maskTexSize": {
        "x": 0,
        "y": 0
    },
    "useProcessedMaskTex": false,
    "isReversedMaskOrder": false,
    "masks": []
}