{
    "namePrefix": "ROOM_104_07",
    "status": 0,
    "bgMd5": "626FDFCECDA7BB30DBFC3D72A446B6C1",
    "bgTexSize": {
        "x": 320,
        "y": 240
    },
    "texDumpMatches": [
        {
            "formatName": "RE1 Classic Rebirth",
            "texNames": [
                "ROOM_104_07"
            ],
            "partIndices": [
                0
            ]
        },
        {
            "formatName": "RE1 TeamX",
            "texNames": [
                "bkg_1047"
            ],
            "partIndices": [
                0
            ]
        }
    ],
    "hasMask": false,
    "camPosIndex": 0,
    "groupsCount": 0,
    "maskMd5": "",
    "maskTexSize": {
        "x": 0,
        "y": 0
    },
    "useProcessedMaskTex": false,
    "isReversedMaskOrder": false,
    "masks": []
}